{"A-B":[{"code":"02954","name":"新奥能源(临时)","parentId":5,"parentName":"香港主板","prevCode":"02951"},{"code":"08213","name":"惟膳","parentId":6,"parentName":"香港创业板","prevCode":"08212"},{"code":"08336","name":"电讯数码控股","parentId":6,"parentName":"香港创业板","prevCode":"08335"}],"B-A":[{"code":"002877","name":"智能自控","parentId":2,"parentName":"中小企业板","prevCode":"002876","orgId":"9900031501","pinyin":"znzk"},{"code":"002878","name":"元隆雅图","parentId":2,"parentName":"中小企业板","prevCode":"002877","orgId":"9900030663","pinyin":"ylyt"},{"code":"300661","name":"圣邦股份","parentId":3,"parentName":"创业板","prevCode":"300660","orgId":"9900024859","pinyin":"sbgf"},{"code":"300662","name":"科锐国际","parentId":3,"parentName":"创业板","prevCode":"300661","orgId":"9900031462","pinyin":"krgj"},{"code":"300663","name":"科蓝软件","parentId":3,"parentName":"创业板","prevCode":"300662","orgId":"9900031461","pinyin":"klrj"},{"code":"08213","name":"新智控股","parentId":6,"parentName":"香港创业板","prevCode":"08212","orgId":"gshk0008213","pinyin":"xzkg"}]}